suds_requests.py
suds_requests4-1.0.1.dist-info/LICENSE
suds_requests4-1.0.1.dist-info/METADATA
suds_requests4-1.0.1.dist-info/WHEEL
suds_requests4-1.0.1.dist-info/top_level.txt
suds_requests4-1.0.1.dist-info/RECORD
