Metadata-Version: 2.1
Name: suds-requests4
Version: 1.0.1
Summary: A suds transport implemented with requests using suds-community
Home-page: https://github.com/genusistimelord/suds_requests4
Author: Jason Michalski
Author-email: jmrosal@crosal-research.com
License: MIT
Platform: UNKNOWN
Requires-Python: >=3.7
